pymodaq_plugins_piezosystemjena/VERSION
pymodaq_plugins_piezosystemjena/__init__.py
pymodaq_plugins_piezosystemjena/daq_move_plugins/__init__.py
pymodaq_plugins_piezosystemjena/daq_move_plugins/daq_move_nv403cle.py
pymodaq_plugins_piezosystemjena/daq_viewer_plugins/__init__.py
pymodaq_plugins_piezosystemjena/daq_viewer_plugins/plugins_0D/__init__.py
pymodaq_plugins_piezosystemjena/daq_viewer_plugins/plugins_1D/__init__.py
pymodaq_plugins_piezosystemjena/daq_viewer_plugins/plugins_2D/__init__.py
pymodaq_plugins_piezosystemjena/daq_viewer_plugins/plugins_ND/__init__.py
pymodaq_plugins_piezosystemjena/hardware/Serial_NV403CLE.py
pymodaq_plugins_piezosystemjena/hardware/__init__.py
pymodaq_plugins_piezosystemjena-0.1.0.dist-info/LICENSE
pymodaq_plugins_piezosystemjena-0.1.0.dist-info/METADATA
pymodaq_plugins_piezosystemjena-0.1.0.dist-info/WHEEL
pymodaq_plugins_piezosystemjena-0.1.0.dist-info/entry_points.txt
pymodaq_plugins_piezosystemjena-0.1.0.dist-info/top_level.txt
pymodaq_plugins_piezosystemjena-0.1.0.dist-info/RECORD
