Metadata-Version: 2.1
Name: pymodaq-plugins-piezosystemjena
Version: 0.1.0
Summary: Pymodaq Plugin for the Control of Piezosystem Jena microscopy stages
Home-page: https://github.com/NT/pymodaq_plugins
Author: Nicolas Tappy
Author-email: nicolas.tappy@epfl.ch
License: CECILL B
Classifier: Programming Language :: Python :: 3
Classifier: Development Status :: 4 - Beta
Classifier: Environment :: Other Environment
Classifier: Intended Audience :: Science/Research
Classifier: Topic :: Scientific/Engineering :: Human Machine Interfaces
Classifier: Topic :: Scientific/Engineering :: Visualization
Classifier: License :: OSI Approved :: MIT License
Classifier: Operating System :: OS Independent
Classifier: Topic :: Software Development :: Libraries :: Python Modules
Classifier: Topic :: Software Development :: User Interfaces
License-File: LICENSE
Requires-Dist: toml
Requires-Dist: pyserial
